<?xml version="1.0" encoding="UTF-8"?>
<xml language="cnh">
<file id="1">
  <head>
    <url>http://www.ted.com/talks/derek_sivers_how_to_start_a_movement?language=cnh</url>
    <pagesize>85171</pagesize>
    <dtime>Sat Apr 21 02:10:35 CEST 2018</dtime>
    <encoding>UTF-8</encoding>
    <content-type>text/html; charset=utf-8</content-type>
    <keywords>talks, business, dance, entertainment, leadership, marketing, online video</keywords>
    <speaker>Dereck Sivers</speaker>
    <talkid>814</talkid>
    <videourl>https://download.ted.com/talks/DerekSivers_2010U.mp4</videourl>
    <videopath>talks/DerekSivers_2010U.mp4</videopath>
    <date>2010/02/11</date>
    <description>TED Talk Subtitles and Transcript: Khuaruah le zoh nuam taktak a simi muicuang hmanthlak he Derek Sivers nih zeitindah cawlcanghnak hi thawk a si timi fiangfai taktak a langhter. (Chikhat lanwg asi ko).</description>
    <title>Dereck Sivers: Cawlcanghnak Thawkning</title>
    <transcription>
      <seekvideo id="1">Upatmi nu le pa hna, TED ahhin thithruainak le cawlcanghnak</seekvideo>
      <seekvideo id="2">thawkning tampi kan chim ve.</seekvideo>
      <seekvideo id="3">Cuca'h, cawlcanghnak thawkning hram in dongh tiang</seekvideo>
      <seekvideo id="4">minute 3 chungah zoh u sih</seekvideo>
      <seekvideo id="5">i, cu chungin cawnnak ilak hna u sih.</seekvideo>
      <seekvideo id="6">Ahmasaah, nan hngalh bangin</seekvideo>
      <seekvideo id="7">hruaitu nih intuarnak caah ralthatnak aherh.</seekvideo>
      <seekvideo id="8">Zohmanh, a tuahmi hi zulh a fawite.</seekvideo>
      <seekvideo id="9">Hi ahhin a zultu hmasa nih biapi thil a tuah;</seekvideo>
      <seekvideo id="10">Hnuzulh dan kha hawidang a hmuhsak hna.</seekvideo>
      <seekvideo id="11">Amah cu hruaitu nih hruaitu bangin a upat kan hmuh;</seekvideo>
      <seekvideo id="12">Atu cu hruaitu kong asi ti lai lo;</seekvideo>
      <seekvideo id="13">Anmah kong asi lai, atammi.</seekvideo>
      <seekvideo id="14">Zoh, a hawidang a kawh cang hna,</seekvideo>
      <seekvideo id="15">Nan hngalh khawh ahcun, apakhatnak zultu</seekvideo>
      <seekvideo id="16">zei ah rel lomi santlailo dirhmun ah chiah asi khi.</seekvideo>
      <seekvideo id="17">Hitin um khawh dingah ralthatnak aherh.</seekvideo>
      <seekvideo id="18">hmasabik hruaitu khi hawidang hna hruaitu ah sertu taktak cu asi.</seekvideo>
      <seekvideo id="19">(Nihthawng)</seekvideo>
      <seekvideo id="20">(Kutbenghthawng)</seekvideo>
      <seekvideo id="21">Cun, tucu pahnihnak zultu a ra cang.</seekvideo>
      <seekvideo id="22">Tucu, santlailo pahnih an um cang—</seekvideo>
      <seekvideo id="23">Pathum cu mibu an si cang, i mibu cu thawngpang a si.</seekvideo>
      <seekvideo id="24">Cucaah, cawlcanghnak cu zapi he aa san.</seekvideo>
      <seekvideo id="25">Hruaitu lawng siloin zultu hna hmaisuam ve zong abiapi,</seekvideo>
      <seekvideo id="26">zeicatiah, zultuthar nih zultu hmasa hna an izohchunh hna.</seekvideo>
      <seekvideo id="27">Hi, an tam deuh thluahmah cang, tlawmpal ah,</seekvideo>
      <seekvideo id="28">mi pathum an ichap cang.</seekvideo>
      <seekvideo id="29">Thazang a cak tuk cang, tlauh khawh asi tilo.</seekvideo>
      <seekvideo id="30">Tucu, cawlcanghnak a thawk cang.</seekvideo>
      <seekvideo id="31">(Nihthawng)</seekvideo>
      <seekvideo id="32">Si, zohhmanh, mi an tam deuh ahcun,</seekvideo>
      <seekvideo id="33">hna a ngam deuh suaumau.</seekvideo>
      <seekvideo id="34">Tuandeuh ah a thu sasawhmi hna kha,</seekvideo>
      <seekvideo id="35">itel ve an duh cang.</seekvideo>
      <seekvideo id="36">An thiamtuk rih men lai lo, nihsawh an si lai lo.</seekvideo>
      <seekvideo id="37">nain khulhrang in an ti ahcun, zapi lakah an itel ve ko lai.</seekvideo>
      <seekvideo id="38">(Nihthawng)</seekvideo>
      <seekvideo id="39">Cuticun, minute tlawmpal hnuah,</seekvideo>
      <seekvideo id="40">zapi lakah an ipeih thluahmah na hmuh lai</seekvideo>
      <seekvideo id="41">itel ve lo tu kha an duh ti lai lo.</seekvideo>
      <seekvideo id="42">Hihi cawlcanghnak thawkning cu asi.</seekvideo>
      <seekvideo id="43">Asi, hi chungin cawnnak ilak u sih.</seekvideo>
      <seekvideo id="44">Hmasaah, amah lawng in a dir i ankgi loin a lammi</seekvideo>
      <seekvideo id="45">bantuk na si ahcun.</seekvideo>
      <seekvideo id="46">Zultu hmasa pawl kha tlukruannak in na hruai hna aherh kha philh hlah. Afiang. Cawlcanghnak kong asi, nangmah kong asi lo. (Nihthawng) Si, cawn/ilak ding taktak kan hrialh sual kho men.</seekvideo>
      <seekvideo id="47">Abiapibik kan cawn hnga dingmi— na hngalh kho maw?— cu thithruainak cu thangthatnak asi. Asi, a thawk hmasatu cu angki hruklopa asi i amah cu lawmh asi ko lai, nain zulhtu hna nunthlentu taktak cu zultu hmasa khi dakaw asi. i, hruaitu kan si dih aherh timi cawnpiaknak hi sullam a ngeih tuk then lai lo.</seekvideo>
      <seekvideo id="48">Cawlcanghnak thawk nai timh taktak ahcun zulh ding ralthatnak ngei law, zulhning zong cawnpiak hna. Cun, santlailo nih thiltha pakhatkhat an tuah ahcun, zultu tha ah ser khawh izuam colh. Cun, hibantuk tuahnak hmunhma thabik cu TED asi.</seekvideo>
      <seekvideo id="49">Lawmtuk. Kutbenghthawng.</seekvideo>
    </transcription>
    <wordnum>438</wordnum>
    <charnum>2462</charnum>
  </head>
  <content>Upatmi nu le pa hna, TED ahhin thithruainak le cawlcanghnak
thawkning tampi kan chim ve.
Cuca'h, cawlcanghnak thawkning hram in dongh tiang
minute 3 chungah zoh u sih
i, cu chungin cawnnak ilak hna u sih.
Ahmasaah, nan hngalh bangin
hruaitu nih intuarnak caah ralthatnak aherh.
Zohmanh, a tuahmi hi zulh a fawite.
Hi ahhin a zultu hmasa nih biapi thil a tuah;
Hnuzulh dan kha hawidang a hmuhsak hna.
Amah cu hruaitu nih hruaitu bangin a upat kan hmuh;
Atu cu hruaitu kong asi ti lai lo;
Anmah kong asi lai, atammi.
Zoh, a hawidang a kawh cang hna,
Nan hngalh khawh ahcun, apakhatnak zultu
zei ah rel lomi santlailo dirhmun ah chiah asi khi.
Hitin um khawh dingah ralthatnak aherh.
hmasabik hruaitu khi hawidang hna hruaitu ah sertu taktak cu asi.
(Nihthawng)
(Kutbenghthawng)
Cun, tucu pahnihnak zultu a ra cang.
Tucu, santlailo pahnih an um cang—
Pathum cu mibu an si cang, i mibu cu thawngpang a si.
Cucaah, cawlcanghnak cu zapi he aa san.
Hruaitu lawng siloin zultu hna hmaisuam ve zong abiapi,
zeicatiah, zultuthar nih zultu hmasa hna an izohchunh hna.
Hi, an tam deuh thluahmah cang, tlawmpal ah,
mi pathum an ichap cang.
Thazang a cak tuk cang, tlauh khawh asi tilo.
Tucu, cawlcanghnak a thawk cang.
(Nihthawng)
Si, zohhmanh, mi an tam deuh ahcun,
hna a ngam deuh suaumau.
Tuandeuh ah a thu sasawhmi hna kha,
itel ve an duh cang.
An thiamtuk rih men lai lo, nihsawh an si lai lo.
nain khulhrang in an ti ahcun, zapi lakah an itel ve ko lai.
(Nihthawng)
Cuticun, minute tlawmpal hnuah,
zapi lakah an ipeih thluahmah na hmuh lai
itel ve lo tu kha an duh ti lai lo.
Hihi cawlcanghnak thawkning cu asi.
Asi, hi chungin cawnnak ilak u sih.
Hmasaah, amah lawng in a dir i ankgi loin a lammi
bantuk na si ahcun.
Zultu hmasa pawl kha tlukruannak in na hruai hna aherh kha philh hlah. Afiang. Cawlcanghnak kong asi, nangmah kong asi lo. (Nihthawng) Si, cawn/ilak ding taktak kan hrialh sual kho men.
Abiapibik kan cawn hnga dingmi— na hngalh kho maw?— cu thithruainak cu thangthatnak asi. Asi, a thawk hmasatu cu angki hruklopa asi i amah cu lawmh asi ko lai, nain zulhtu hna nunthlentu taktak cu zultu hmasa khi dakaw asi. i, hruaitu kan si dih aherh timi cawnpiaknak hi sullam a ngeih tuk then lai lo.
Cawlcanghnak thawk nai timh taktak ahcun zulh ding ralthatnak ngei law, zulhning zong cawnpiak hna. Cun, santlailo nih thiltha pakhatkhat an tuah ahcun, zultu tha ah ser khawh izuam colh. Cun, hibantuk tuahnak hmunhma thabik cu TED asi.
Lawmtuk. Kutbenghthawng.</content>
</file>
</xml>
